elib_wx/__init__.py
elib_wx/airports.db
elib_wx/airports_db.py
elib_wx/exc.py
elib_wx/static.py
elib_wx/utils.py
elib_wx/weather.py
elib_wx/weather_abc.py
elib_wx/weather_dcs.py
elib_wx/weather_dcs_generate.py
elib_wx/weather_from_icao.py
elib_wx/weather_from_metar_data.py
elib_wx/weather_from_metar_string.py
elib_wx/weather_from_miz.py
elib_wx/weather_to_mission.py
elib_wx/weather_to_miz.py
elib_wx/weather_translate.py
elib_wx/avwx/__init__.py
elib_wx/avwx/core.py
elib_wx/avwx/exceptions.py
elib_wx/avwx/metar.py
elib_wx/avwx/remarks.py
elib_wx/avwx/service.py
elib_wx/avwx/speech.py
elib_wx/avwx/static.py
elib_wx/avwx/structs.py
elib_wx/avwx/summary.py
elib_wx/avwx/taf.py
elib_wx/avwx/translate.py
elib_wx/values/__init__.py
elib_wx/values/value.py
test/__init__.py
test/conftest.py
test/refresh_test_data.py
test/test_data.py
test/utils.py
test/test_avwx/test_core.py
test/test_avwx/test_metar.py
test/test_avwx/test_remarks.py
test/test_avwx/test_service.py
test/test_avwx/test_speech.py
test/test_avwx/test_summary.py
test/test_avwx/test_taf.py
test/test_avwx/test_translate.py
test/test_avwx/test_metar/EGLL.json
test/test_avwx/test_metar/KJFK.json
test/test_avwx/test_metar/KMCO.json
test/test_avwx/test_metar/PHNL.json
test/test_avwx/test_taf/EGLL.json
test/test_avwx/test_taf/KJFK.json
test/test_avwx/test_taf/KMCO.json
test/test_avwx/test_taf/PHNL.json
test/test_files/test_caucasus.miz
test/test_files/test_data
test/test_files/test_nevada.miz
test/test_files/test_persiangulf.miz
test/test_files/test_wx_1.miz
test/test_files/test_wx_heavy_dust.miz
test/test_files/test_wx_snow.miz
test/test_files/test_wx_snowstorm.miz
test/test_files/test_wx_thunderstorm.miz
test/test_weather/test_all_metars.py
test/test_weather/test_from_icao.py
test/test_weather/test_from_miz_file.py
test/test_weather/test_source.py
test/test_weather/test_weather_icao.py
test/test_weather/test_wx_remarks.py
test/test_weather/test_dcs_weather/conftest.py
elib_wx-2018.12.15.2.dist-info/AUTHORS.md
elib_wx-2018.12.15.2.dist-info/LICENSE
elib_wx-2018.12.15.2.dist-info/METADATA
elib_wx-2018.12.15.2.dist-info/WHEEL
elib_wx-2018.12.15.2.dist-info/top_level.txt
elib_wx-2018.12.15.2.dist-info/RECORD
