Metadata-Version: 2.1
Name: elib-wx
Version: 2018.12.15.2
Summary: Weather management lib for DCS
Home-page: https://github.com/etcher-be/elib_wx
Author: etcher
Author-email: etcher@daribouca.net
License: MIT
Download-URL: https://github.com/etcher-be/elib_wx/releases
Platform: win32
Classifier: Development Status :: 3 - Alpha
Classifier: License :: OSI Approved :: MIT License
Classifier: Environment :: Win32 (MS Windows)
Classifier: Natural Language :: English
Classifier: Operating System :: Microsoft :: Windows
Classifier: Operating System :: Microsoft :: Windows :: Windows 7
Classifier: Operating System :: Microsoft :: Windows :: Windows 10
Classifier: Programming Language :: Python
Classifier: Programming Language :: Python :: 3 :: Only
Classifier: Programming Language :: Python :: 3.6
Classifier: Programming Language :: Python :: Implementation
Classifier: Programming Language :: Python :: Implementation :: CPython
Classifier: Topic :: Software Development :: Libraries
Classifier: Topic :: Games/Entertainment :: Simulation
Requires-Python: >=3.6
Requires-Dist: python-dateutil
Requires-Dist: requests
Requires-Dist: xmltodict
Requires-Dist: dataclasses
Requires-Dist: inflect
Requires-Dist: elib-miz
